{
  "conns": 1,
  "tls": false,
  "scenario_set": "core",
  "scenarios": [
    { "name": "SET               size=100     conc=1", "count": 5000, "ops_per_sec": 6722.07, "avg_ms": 0.149, "p50_ms": 0.145, "p90_ms": 0.162, "p99_ms": 0.210, "p999_ms": 0.292, "max_ms": 0.838 },
    { "name": "GET               size=100     conc=1", "count": 5000, "ops_per_sec": 6791.13, "avg_ms": 0.147, "p50_ms": 0.142, "p90_ms": 0.168, "p99_ms": 0.232, "p999_ms": 0.423, "max_ms": 1.521 },
    { "name": "SET               size=100     conc=10", "count": 5000, "ops_per_sec": 28216.73, "avg_ms": 0.354, "p50_ms": 0.349, "p90_ms": 0.472, "p99_ms": 0.613, "p999_ms": 0.937, "max_ms": 1.069 },
    { "name": "GET               size=100     conc=10", "count": 5000, "ops_per_sec": 29698.77, "avg_ms": 0.336, "p50_ms": 0.329, "p90_ms": 0.444, "p99_ms": 0.543, "p999_ms": 0.646, "max_ms": 0.736 },
    { "name": "MIX(80G/20S)      size=100     conc=10", "count": 5000, "ops_per_sec": 29646.84, "avg_ms": 0.337, "p50_ms": 0.332, "p90_ms": 0.443, "p99_ms": 0.536, "p999_ms": 0.648, "max_ms": 0.729 },
    { "name": "SET               size=100     conc=100", "count": 5000, "ops_per_sec": 32718.41, "avg_ms": 3.043, "p50_ms": 3.023, "p90_ms": 4.037, "p99_ms": 4.692, "p999_ms": 5.207, "max_ms": 5.268 },
    { "name": "GET               size=100     conc=100", "count": 5000, "ops_per_sec": 31614.13, "avg_ms": 3.148, "p50_ms": 3.177, "p90_ms": 4.156, "p99_ms": 5.038, "p999_ms": 5.777, "max_ms": 6.068 },
    { "name": "MIX(80G/20S)      size=100     conc=100", "count": 5000, "ops_per_sec": 35195.38, "avg_ms": 2.812, "p50_ms": 2.852, "p90_ms": 3.689, "p99_ms": 4.754, "p999_ms": 5.178, "max_ms": 5.194 },
    { "name": "SET               size=16384   conc=10", "count": 5000, "ops_per_sec": 19596.69, "avg_ms": 0.510, "p50_ms": 0.486, "p90_ms": 0.652, "p99_ms": 1.185, "p999_ms": 1.416, "max_ms": 1.505 },
    { "name": "GET               size=16384   conc=10", "count": 5000, "ops_per_sec": 16969.91, "avg_ms": 0.589, "p50_ms": 0.536, "p90_ms": 0.903, "p99_ms": 1.369, "p999_ms": 1.485, "max_ms": 1.529 },
    { "name": "MIX(80G/20S)      size=1024    conc=100", "count": 5000, "ops_per_sec": 25274.23, "avg_ms": 3.922, "p50_ms": 3.970, "p90_ms": 4.916, "p99_ms": 5.554, "p999_ms": 6.244, "max_ms": 6.467 }
  ]
}
